aqueduct/__init__.py
aqueduct/__main__.py
aqueduct/aqueduct.py
aqueduct/deployment.py
aqueduct/destruction.py
aqueduct/identity.py
aqueduct/validation.py
aqueduct_utility-0.12.0.dist-info/LICENSE
aqueduct_utility-0.12.0.dist-info/METADATA
aqueduct_utility-0.12.0.dist-info/WHEEL
aqueduct_utility-0.12.0.dist-info/entry_points.txt
aqueduct_utility-0.12.0.dist-info/top_level.txt
aqueduct_utility-0.12.0.dist-info/RECORD
