Metadata-Version: 2.1
Name: aqueduct-utility
Version: 0.12.0
Summary: Cloud Development Kit Toolbox
Home-page: https://github.com/jblukach/aqueduct.git
Author: John Lukach
Author-email: hello@lukach.io
License: Apache-2.0
Requires-Python: >=3.7
License-File: LICENSE
Requires-Dist: aws-sso-lib
Requires-Dist: typer[all]
